monocdk_experiment/__init__.py
monocdk_experiment/py.typed
monocdk_experiment/_jsii/__init__.py
monocdk_experiment/_jsii/monocdk-experiment@1.66.0.jsii.tgz
monocdk_experiment/alexa_ask/__init__.py
monocdk_experiment/app_delivery/__init__.py
monocdk_experiment/assets/__init__.py
monocdk_experiment/aws_accessanalyzer/__init__.py
monocdk_experiment/aws_acmpca/__init__.py
monocdk_experiment/aws_amazonmq/__init__.py
monocdk_experiment/aws_amplify/__init__.py
monocdk_experiment/aws_apigateway/__init__.py
monocdk_experiment/aws_apigatewayv2/__init__.py
monocdk_experiment/aws_appconfig/__init__.py
monocdk_experiment/aws_appflow/__init__.py
monocdk_experiment/aws_applicationautoscaling/__init__.py
monocdk_experiment/aws_applicationinsights/__init__.py
monocdk_experiment/aws_appmesh/__init__.py
monocdk_experiment/aws_appstream/__init__.py
monocdk_experiment/aws_appsync/__init__.py
monocdk_experiment/aws_athena/__init__.py
monocdk_experiment/aws_autoscaling/__init__.py
monocdk_experiment/aws_autoscaling_common/__init__.py
monocdk_experiment/aws_autoscaling_hooktargets/__init__.py
monocdk_experiment/aws_autoscalingplans/__init__.py
monocdk_experiment/aws_backup/__init__.py
monocdk_experiment/aws_batch/__init__.py
monocdk_experiment/aws_budgets/__init__.py
monocdk_experiment/aws_cassandra/__init__.py
monocdk_experiment/aws_ce/__init__.py
monocdk_experiment/aws_certificatemanager/__init__.py
monocdk_experiment/aws_chatbot/__init__.py
monocdk_experiment/aws_cloud9/__init__.py
monocdk_experiment/aws_cloudformation/__init__.py
monocdk_experiment/aws_cloudfront/__init__.py
monocdk_experiment/aws_cloudfront_origins/__init__.py
monocdk_experiment/aws_cloudtrail/__init__.py
monocdk_experiment/aws_cloudwatch/__init__.py
monocdk_experiment/aws_cloudwatch_actions/__init__.py
monocdk_experiment/aws_codebuild/__init__.py
monocdk_experiment/aws_codecommit/__init__.py
monocdk_experiment/aws_codedeploy/__init__.py
monocdk_experiment/aws_codeguruprofiler/__init__.py
monocdk.experiment-1.66.0.dist-info/METADATA
monocdk.experiment-1.66.0.dist-info/WHEEL
monocdk.experiment-1.66.0.dist-info/top_level.txt
monocdk.experiment-1.66.0.dist-info/RECORD
