Metadata-Version: 2.1
Name: monocdk.experiment
Version: 1.66.0
Summary: An experiment to bundle the entire CDK into a single module
Home-page: https://github.com/aws/aws-cdk
Author: Amazon Web Services
License: Apache-2.0
Project-URL: Source, https://github.com/aws/aws-cdk.git
Platform: UNKNOWN
Classifier: Intended Audience :: Developers
Classifier: Operating System :: OS Independent
Classifier: Programming Language :: JavaScript
Classifier: Programming Language :: Python :: 3 :: Only
Classifier: Programming Language :: Python :: 3.6
Classifier: Programming Language :: Python :: 3.7
Classifier: Programming Language :: Python :: 3.8
Classifier: Typing :: Typed
Classifier: Development Status :: 4 - Beta
Classifier: License :: OSI Approved
Requires-Python: >=3.6
Requires-Dist: constructs (<4.0.0,>=3.0.4)
Requires-Dist: jsii (<2.0.0,>=1.13.0)
Requires-Dist: publication (>=0.0.3)
